{
    "models": [
        {
            "name": "Unity_Builtin_Cube",
            "guid": "0000000000000000e000000000000000"
        },
        {
            "name": "Decor_Doorframe_Single",
            "guid": "0e0ca3c62a03d644da2187399aab477a"
        },
        {
            "name": "FloorTile_Slab_10x10",
            "guid": "ea2f01651cae4b54988d1b3f8b7a17e7"
        },
        {
            "name": "Room_Mid_Ramp1",
            "guid": "7fb34cb24a7127349b2aa02721871bcd"
        },
        {
            "name": "Room_Mid_Roof",
            "guid": "add0984f21a946c4d9076c476e68d2c4"
        },
        {
            "name": "Room_Mid_Roof_Stair1",
            "guid": "4a694ceae68c87c4b9ff048b5f51f4f7"
        },
        {
            "name": "Room_Mid_Wall",
            "guid": "24dcadf81b775fe47bd5e0685eb372a5"
        },
        {
            "name": "Room_Mid_Wall_Door",
            "guid": "7efa42e69f158b3418712c3d27a67c8e"
        },
        {
            "name": "Room_Mid_Wall_Window",
            "guid": "05aad97317c124741a2520a9881a1afd"
        },
        {
            "name": "Room_Mid_Window1",
            "guid": "256054a64dbafae469c7e161d7f5379d"
        },
        {
            "name": "Ramp",
            "guid": "24c333ebd9de243408b9fd68e57b5290"
        }
    ],
    "materials": [
        {
            "Name": "Wall1",
            "GUID": "b7540bbafd5d39341ab34852c651160d",
            "AlbedoMap": "textures/Wall1_Diff+Spec",
            "NormalMap": "textures/Wall1_Bump"
        },
        {
            "Name": "Wall2",
            "GUID": "107eee8dc45625b44a144a214d8d7b31",
            "AlbedoMap": "textures/Wall2_Halfblock_Diff+Spec",
            "NormalMap": "textures/Wall2_Halfblock_Bump"
        },
        {
            "Name": "Floor1",
            "GUID": "a279ff533c8c0d1408b26d70a2693428",
            "AlbedoMap": "textures/Floor1_Diff+Spec",
            "NormalMap": "textures/Floor1_Bump"
        },
        {
            "Name": "Floor3",
            "GUID": "5a92d152b0a4b8f41a4e549b3a63a4e7",
            "AlbedoMap": "textures/Floor3_Diff+Spec",
            "NormalMap": "textures/Floor3_Bump"
        },
        {
            "Name": "Wall1_Halfblock",
            "GUID": "545cf3d8cf1375b4395aa95b6022bca9",
            "AlbedoMap": "textures/Wall1_Halfblock_Diff+Spec",
            "NormalMap": "textures/Wall1_Halfblock_Bump"
        },
        {
            "Name": "Glass",
            "GUID": "8000864a8a175df468a93306d9605197",
            "AlbedoMap": "textures/Glass_Diff+Spec",
            "NormalMap": ""
        },
        {
            "Name": "Floor3_Diff",
            "GUID": "e758d54a1ae70f142aec3bde8c97f713",
            "AlbedoMap": "",
            "NormalMap": ""
        },
        {
            "Name": "Wall1_Diff",
            "GUID": "9bb23e67cef5af04088ee281a40b60b7",
            "AlbedoMap": "",
            "NormalMap": ""
        },
        {
            "Name": "lambert1",
            "GUID": "704f6d686747cad42a5813085cedc419",
            "AlbedoMap": "",
            "NormalMap": ""
        }
    ],
    "textures": [
        {
            "Path": "textures/Wall1_Diff+Spec",
            "GUID": "2b3b7bc7498198b4d996d8c918eaf453",
            "Dimension": "tex2d",
            "WrapMode": "repeat",
            "FilterMode": "bilinear",
            "MipmapCount": 10,
            "MipmapBias": 0.0
        },
        {
            "Path": "textures/Wall1_Bump",
            "GUID": "f7f8e34c49bb0d24593f5a03458f330b",
            "Dimension": "tex2d",
            "WrapMode": "repeat",
            "FilterMode": "trilinear",
            "MipmapCount": 10,
            "MipmapBias": 0.0
        },
        {
            "Path": "textures/Wall2_Halfblock_Diff+Spec",
            "GUID": "6604aaacb9f1558449abfc0c6d2e0570",
            "Dimension": "tex2d",
            "WrapMode": "repeat",
            "FilterMode": "bilinear",
            "MipmapCount": 10,
            "MipmapBias": 0.0
        },
        {
            "Path": "textures/Wall2_Halfblock_Bump",
            "GUID": "cd43279f80e31604e86e8208bdea472b",
            "Dimension": "tex2d",
            "WrapMode": "repeat",
            "FilterMode": "trilinear",
            "MipmapCount": 10,
            "MipmapBias": 0.0
        },
        {
            "Path": "textures/Floor1_Diff+Spec",
            "GUID": "cc39a17532b382042b971e892c29aee4",
            "Dimension": "tex2d",
            "WrapMode": "repeat",
            "FilterMode": "bilinear",
            "MipmapCount": 11,
            "MipmapBias": 0.0
        },
        {
            "Path": "textures/Floor1_Bump",
            "GUID": "d4953f7c4b5211a4d880b0889f5e31b4",
            "Dimension": "tex2d",
            "WrapMode": "repeat",
            "FilterMode": "trilinear",
            "MipmapCount": 11,
            "MipmapBias": 0.0
        },
        {
            "Path": "textures/Floor3_Diff+Spec",
            "GUID": "65cacb3b8f364b24eb7ea5b180888e56",
            "Dimension": "tex2d",
            "WrapMode": "repeat",
            "FilterMode": "bilinear",
            "MipmapCount": 10,
            "MipmapBias": 0.0
        },
        {
            "Path": "textures/Floor3_Bump",
            "GUID": "26dee1916efb09d449d76fb70fac9713",
            "Dimension": "tex2d",
            "WrapMode": "repeat",
            "FilterMode": "trilinear",
            "MipmapCount": 10,
            "MipmapBias": 0.0
        },
        {
            "Path": "textures/Wall1_Halfblock_Diff+Spec",
            "GUID": "bfc299e710cbe2641ad50610fef623f6",
            "Dimension": "tex2d",
            "WrapMode": "repeat",
            "FilterMode": "bilinear",
            "MipmapCount": 10,
            "MipmapBias": 0.0
        },
        {
            "Path": "textures/Wall1_Halfblock_Bump",
            "GUID": "60ccac5034367c44f8cb9ac8d4d81288",
            "Dimension": "tex2d",
            "WrapMode": "repeat",
            "FilterMode": "trilinear",
            "MipmapCount": 10,
            "MipmapBias": 0.0
        },
        {
            "Path": "textures/Glass_Diff+Spec",
            "GUID": "a7487e05b56a4a445983027338aef12d",
            "Dimension": "tex2d",
            "WrapMode": "repeat",
            "FilterMode": "bilinear",
            "MipmapCount": 9,
            "MipmapBias": 0.0
        }
    ]
}